CHANGELOG.rst
LICENSE
MANIFEST.in
README.rst
requirements.txt
setup.cfg
setup.py
consul/__init__.py
consul/aio.py
consul/base.py
consul/std.py
consul/tornado.py
consul/twisted.py
habibutsu.python_consul.egg-info/PKG-INFO
habibutsu.python_consul.egg-info/SOURCES.txt
habibutsu.python_consul.egg-info/dependency_links.txt
habibutsu.python_consul.egg-info/requires.txt
habibutsu.python_consul.egg-info/top_level.txt