Metadata-Version: 2.1
Name: habibutsu.python-consul
Version: 1.2.0
Summary: Python client for Consul (http://www.consul.io/)
Home-page: https://github.com/habibutsu/python-consul
Author: Andy Gayton
Author-email: andy@thecablelounge.com
Maintainer: Alexander Verbitsky
Maintainer-email: habibutsu@gmail.com
License: MIT
Platform: UNKNOWN
Classifier: Development Status :: 3 - Alpha
Classifier: Intended Audience :: Developers
Classifier: License :: OSI Approved :: MIT License
Classifier: Programming Language :: Python :: 2
Classifier: Programming Language :: Python :: 2.7
Classifier: Programming Language :: Python :: 3
Classifier: Programming Language :: Python :: 3.5
Classifier: Programming Language :: Python :: 3.6
Provides-Extra: tornado
Provides-Extra: asyncio
Provides-Extra: twisted
